<?xml version="1.0" encoding="UTF-8"?>
<!DOCTYPE suite SYSTEM "C:\ECLIPSE-PROJECTS\SeleniumframeworkDesign\testng-1.0.dtd">
<suite parallel="tests" name="Suite">

<groups>
<run>
	<include name="Purchase"/>
</run>
</groups>

<listeners>
<listener class-name="sujaniacademy.tests.testcomponenets.Listeners"></listener>
</listeners>

  <test thread-count="5" name="Submit Order Test">
    <classes>      
      <class name="sujaniacademy.tests.SubmitOrderTest"/>
    </classes>
  </test> 
  
  <test thread-count="5" name="Error Validation Test">
    <classes>      
      <class name="sujaniacademy.tests.ErrorValidationsTest"/>
    </classes>
  </test>

</suite> <!-- Suite -->
